poker_now_log_converter/__init__.py
poker_now_log_converter/__main__.py
poker_now_log_converter/action.py
poker_now_log_converter/card.py
poker_now_log_converter/game.py
poker_now_log_converter/hand.py
poker_now_log_converter/main.py
poker_now_log_converter/player.py
poker_now_log_converter/seat.py
poker_now_log_converter/utils.py
poker_now_log_converter-0.0.14.dist-info/LICENSE.TXT
poker_now_log_converter-0.0.14.dist-info/METADATA
poker_now_log_converter-0.0.14.dist-info/WHEEL
poker_now_log_converter-0.0.14.dist-info/top_level.txt
poker_now_log_converter-0.0.14.dist-info/RECORD
