Metadata-Version: 2.1
Name: poker_now_log_converter
Version: 0.0.14
Summary: A simple command line utility for converting logs from Poker Now games to other formats
Home-page: https://github.com/charlestudor/PokerNowLogConverter
Author: Charles Tudor
Author-email: mail@ctudor.net
Classifier: Programming Language :: Python :: 3.8
Classifier: Programming Language :: Python :: 3.9
Classifier: Programming Language :: Python :: 3.10
Classifier: Programming Language :: Python :: 3.11
Classifier: License :: OSI Approved :: MIT License
Classifier: Operating System :: OS Independent
Requires-Python: >=3.8
License-File: LICENSE.TXT
